{"argMax":-1,"keywords":["array"],"arguments":[{"required":true,"status":"implemeted","name":"haystack","type":"array","description":"The array in which to search for the item","defaultValue":null},{"required":true,"status":"implemeted","name":"needle","type":"object","description":"The item that we are looking for in the array","defaultValue":null},{"required":false,"status":"implemeted","name":"substringMatch","type":"boolean","description":"If set to true then if a then a substring match will also return true. This will only work with simple values. Passing true with complex objects will throw an exception.","defaultValue":null}],"argMin":2,"returnType":"number","status":"implemeted","name":"arraycontains","type":"java","argumentType":"fixed","description":"Returns the position of the first element in the array that matches the item that we are searching for, or 0 if the item is not found.","member":{"position":1,"chaining":false,"name":"contains","type":"array"}}