{"argMax":-1,"keywords":["array"],"arguments":[{"required":true,"status":"implemeted","name":"array","type":"array","description":"The array to delete from","defaultValue":null},{"required":true,"status":"implemeted","name":"value","type":"object","description":"The value to delete","defaultValue":null},{"required":false,"status":"implemeted","name":"scope","type":"string","description":"one: replaces the first occurrence (default)\n\t\t\t\tall: replaces all occurrences","defaultValue":null}],"argMin":2,"returnType":"boolean","status":"implemeted","name":"arraydelete","type":"java","argumentType":"fixed","description":"Deletes specified object from given array","member":{"position":1,"chaining":false,"name":"delete","type":"array"}}