{"argMax":-1,"keywords":["string"],"arguments":[{"required":true,"status":"implemeted","name":"string","type":"string","description":"A string","defaultValue":null},{"required":false,"status":"implemeted","name":"position","type":"number","description":"Position of the character","defaultValue":"1"}],"argMin":1,"returnType":"number","status":"implemeted","name":"asc","type":"java","argumentType":"fixed","description":"Determines the value of a character.","member":{"position":1,"chaining":false,"name":"asc","type":"string"}}