{"argMax":-1,"keywords":["string"],"arguments":[{"required":true,"status":"implemeted","name":"string1","type":"string","description":"A string or a variable that contains one","defaultValue":null},{"required":true,"status":"implemeted","name":"string2","type":"string","description":"A string or a variable that contains one","defaultValue":null}],"argMin":2,"returnType":"number","status":"implemeted","name":"compare","type":"java","argumentType":"fixed","description":"Performs a case-sensitive comparison of two strings.\n            -1, if string1 is less than string2\n            0, if string1 is equal to string2\n            1, if string1 is greater than string2","member":{"position":1,"chaining":false,"name":"compare","type":"string"}}