{"argMax":-1,"arguments":[{"required":true,"status":"implemeted","name":"path","type":"string","description":"An absolute path. Alternatively, you can specify IP address as in the following example: DirectoryExists(\\\"//12.3.123.123/c_drive/test\\\");","defaultValue":null},{"required":false,"status":"implemeted","name":"allowRealPath","type":"object","description":"boolean that defines if relative paths are interpreted or not","defaultValue":null}],"argMin":1,"returnType":"boolean","status":"implemeted","name":"directoryexists","type":"java","argumentType":"fixed","description":"Determines whether a directory exists."}