{"argMax":-1,"keywords":["number","math"],"arguments":[{"required":true,"status":"implemeted","name":"number","type":"number","description":"Exponent to apply to the base e","defaultValue":null}],"argMin":1,"returnType":"number","status":"implemeted","name":"exp","type":"java","argumentType":"fixed","description":"Calculates the exponent whose base is e that represents number.\n        The constant e equals 2.71828182845904, the base of the natural\n        logarithm. This function is the inverse of Log, the natural\n        logarithm of number."}