{"argMax":-1,"arguments":[{"required":true,"status":"implemeted","name":"spreadSheet","type":"excel","description":"","defaultValue":null},{"required":true,"status":"implemeted","name":"value","type":"string","description":"","defaultValue":null},{"required":true,"status":"implemeted","name":"row","type":"number","description":"","defaultValue":null},{"required":true,"status":"implemeted","name":"column","type":"number","description":"","defaultValue":null}],"argMin":4,"returnType":"void","status":"implemeted","name":"spreadsheetsetcellvalue","type":"java","argumentType":"fixed","description":""}