{"argumentType":"fixed","arguments":[{"status":"implemeted","description":"","name":"scope","type":"string","required":true},{"status":"implemeted","description":"","name":"encoding","type":"string","required":true}],"argMin":2,"status":"implemeted","description":"Sets the character encoding (character set) of Form and URL\n        scope variable values; used when the character encoding of\n        the input to a form, or the character encoding of a URL, is\n        not in UTF-8 encoding.","name":"setencoding","type":"java","argMax":-1,"returnType":"string"}