{"returnType":"void","status":"implemeted","arguments":[{"status":"implemeted","description":"The image on which this operation is performed.","name":"name","type":"any","required":true},{"status":"implemeted","description":"Background color (The default value is \"black\"):\n- Hexadecimal value of RGB color. For example, specify the color white as ##FFFFFF or FFFFFF.\n- String value of color (for example, \"black\", \"red\", \"green\"). \n- List of three numbers for (R,G,B) values. Each value must be in the range 0-255.","name":"color","type":"string","required":true}],"description":"Sets the background color for the image. The background color is used for clearing a region. Setting the background color only affects the subsequent ImageClearRect calls","argMax":-1,"name":"imagesetbackgroundcolor","argMin":2,"type":"java","argumentType":"fixed"}