{"returnType":"struct","status":"implemeted","arguments":[{"status":"implemeted","description":"The XML to validate","name":"xmlDoc","type":"string","required":true},{"status":"implemeted","description":"Any of the following:\n - A string containing a DTD or Schema.\n - The name of a DTD or Schema file.\n - The URL of a DTD or Schema file; valid protocol identifiers include http, https, ftp, and file.","name":"validator","type":"string","required":false}],"description":"Uses a Document Type Definition (DTD) or XML Schema to validate an XML text document or an XML document object.","argMax":-1,"name":"xmlvalidate","argMin":1,"type":"java","argumentType":"fixed"}