{"bodyType":"prohibited","attrMax":0,"parseBody":false,"status":"implemeted","attrMin":0,"hasNameAppendix":false,"name":"videoplayerparam","type":"java","attributeCollection":true,"attributeType":"fixed","nameSpaceSeperator":"","attributes":{"show":{"required":false,"status":"implemeted","scriptSupport":"none","type":"string","description":"Defines whether the video should be displayed or not."},"flash":{"required":false,"status":"implemeted","scriptSupport":"none","type":"string","description":"Path to the SWF file. Can be a URL or local file."},"image":{"required":false,"status":"implemeted","scriptSupport":"none","type":"string","description":"This is just an alias for the attribute preview."},"index":{"required":false,"status":"implemeted","scriptSupport":"none","type":"number","description":"Layer in which the video is displayed. (not supported yet)"},"link":{"required":false,"status":"implemeted","scriptSupport":"none","type":"string","description":"Displays a tiny image and allows linking to any target. (HTML link, Ajax etc.)"},"video":{"required":false,"status":"implemeted","scriptSupport":"none","type":"string","description":"Path to the FLV file. Can be a URL or local file."},"author":{"required":false,"status":"implemeted","scriptSupport":"none","type":"string","description":"Name of the author."},"title":{"required":false,"status":"implemeted","scriptSupport":"none","type":"string","description":"Title of the video. Displayed in the playlist as the title."},"preview":{"required":false,"status":"implemeted","scriptSupport":"none","type":"string","description":"Path to a preview image for playlist and main video display. Can be URL or local file."}},"description":"play a video","nameSpace":"cf"}