{"bodyType":"free","attrMax":0,"parseBody":false,"script":{"singletype":"required","type":"single","rtexpr":true},"status":"implemeted","attrMin":0,"hasNameAppendix":false,"name":"pageencoding","type":"java","attributeCollection":true,"attributeType":"fixed","nameSpaceSeperator":"","attributes":{"charset":{"required":true,"status":"implemeted","scriptSupport":"required","type":"string","description":"A string literal; the character encoding to use to read the page. The value may be enclosed in single or double quotation marks, or none."}},"description":"A string literal; the character encoding to use to read the page. The value may be enclosed in single or double quotation marks, or none.","nameSpace":"cf"}